tovana/__init__.py
tovana/memory.py
tovana/llms/__init__.py
tovana/llms/llms.py
tovana-0.0.9.dist-info/LICENSE
tovana-0.0.9.dist-info/METADATA
tovana-0.0.9.dist-info/WHEEL
tovana-0.0.9.dist-info/top_level.txt
tovana-0.0.9.dist-info/RECORD
