Metadata-Version: 2.1
Name: tovana
Version: 0.0.9
Summary: Memory management library to enhance AI agents with smarter, personalized, context-aware responses
Home-page: https://github.com/assafelovic/tovana
Author: Assaf Elovic
Author-email: assaf.elovic@gmail.com
License: Apache License 2.0
Classifier: Programming Language :: Python :: 3
Classifier: License :: OSI Approved :: Apache Software License
Classifier: Operating System :: OS Independent
Requires-Python: >=3.10
License-File: LICENSE
Requires-Dist: langchain
Requires-Dist: langchain-openai
Requires-Dist: aiofiles
